moko/__init__.py
moko/configure.py
moko/dict.py
moko/moko.py
moko/moko_test.py
moko/noun_chunker.py
moko/processor.py
moko/term_analyzer.py
moko/util_io.py
moko/utils_io.py
moko/data/__init__.py
moko/data/adverb.txt
moko/data/char_synonym.txt
moko/data/chunk_lst.csv
moko/data/editorial_spacing_rules.txt
moko/data/editorial_training.txt
moko/data/entities.csv
moko/data/stopword.txt
moko/data/user_dict.txt
moko/model/__init__.py
moko/model/soyspacing_model
moko-0.1.0.16.dist-info/METADATA
moko-0.1.0.16.dist-info/WHEEL
moko-0.1.0.16.dist-info/top_level.txt
moko-0.1.0.16.dist-info/RECORD
