Metadata-Version: 2.1
Name: moko
Version: 0.1.0.16
Summary: Modern Korean NLP Package
Home-page: https://cmks.yonsei.ac.kr/cmks/database.htm?ch=2
Author: yk.jeong, m.kim
Author-email: yookyungjeong@gmail.com, munui0822@gmail.com
License: MIT License
Requires-Python: >=3.6
Requires-Dist: soyspacing
Requires-Dist: hanja
